nsdlib/__init__.py
nsdlib/commons.py
nsdlib/setup.py
nsdlib/source_detection.py
nsdlib/taxonomies.py
nsdlib/version.py
nsdlib/algorithms/__init__.py
nsdlib/algorithms/algorithms_utils.py
nsdlib/algorithms/evaluation/__init__.py
nsdlib/algorithms/evaluation/dynamic_age.py
nsdlib/algorithms/evaluation/jordan_center.py
nsdlib/algorithms/evaluation/net_sleuth.py
nsdlib/algorithms/outbreaks/__init__.py
nsdlib/algorithms/reconstruction/__init__.py
nsdlib/algorithms/reconstruction/sbrp.py
nsdlib/algorithms/reconstruction/utils.py
nsdlib/common/__init__.py
nsdlib/common/exceptions.py
nsdlib/common/models.py
nsdlib/common/nx_utils.py
nsdlib-0.1.2.dist-info/LICENSE
nsdlib-0.1.2.dist-info/METADATA
nsdlib-0.1.2.dist-info/WHEEL
nsdlib-0.1.2.dist-info/top_level.txt
nsdlib-0.1.2.dist-info/RECORD
