Metadata-Version: 2.1
Name: nsdlib
Version: 0.1.2
Summary: Network source detection library
Home-page: https://github.com/damianfraszczak/nsdlib
Author: Damian Frąszczak, Edyta Frąszczak
Author-email: damian.fraszczak@wat.edu.pl
License: MIT
Keywords: propagation-source-detection outbreaks-detection propagation-reconstruction complex-networks
Classifier: Development Status :: 4 - Beta
Classifier: Intended Audience :: Developers
Classifier: Topic :: Software Development :: Build Tools
Classifier: License :: OSI Approved :: MIT License
Classifier: Programming Language :: Python
Classifier: Programming Language :: Python :: 3
License-File: LICENSE
Requires-Dist: networkx >=3.0
Requires-Dist: numpy
Requires-Dist: scipy
Provides-Extra: lint
Requires-Dist: bandit ; extra == 'lint'
Requires-Dist: black ; extra == 'lint'
Requires-Dist: flake8 ; extra == 'lint'
Requires-Dist: flake8-debugger ; extra == 'lint'
Requires-Dist: flake8-docstrings ; extra == 'lint'
Requires-Dist: flake8-isort ; extra == 'lint'
Requires-Dist: mypy ; extra == 'lint'
Requires-Dist: pylint ; extra == 'lint'
